Metadata-Version: 2.1
Name: SBMLLint
Version: 1.1.2
Summary: Linter for SBML models.
Home-page: https://github.com/ModelEngineering/SBMLLint
Author: Woosub Shin, Joseph L. Hellerstein
Author-email: jlheller@uw.edu
License: UNKNOWN
Platform: UNKNOWN
Classifier: Development Status :: 3 - Alpha
Classifier: Intended Audience :: Developers
Classifier: Topic :: Scientific/Engineering :: Bio-Informatics
Classifier: License :: OSI Approved :: MIT License
Classifier: Programming Language :: Python :: 3.4
Classifier: Programming Language :: Python :: 3.5
Classifier: Programming Language :: Python :: 3.6
Classifier: Programming Language :: Python :: 3.7
Classifier: Programming Language :: Python :: 3.8
